{
  "schema_version": "article-archive.v1",
  "document_id": "lilian-weng:2017-08-01-interpretation",
  "title": "如何解释机器学习模型的预测？",
  "title_zh": "如何解释机器学习模型的预测？",
  "title_en": "How to Explain the Prediction of a Machine Learning Model?",
  "source_url": "https://lilianweng.github.io/posts/2017-08-01-interpretation/",
  "author": "Lilian Weng",
  "published_at": "2017-08-01",
  "source_revision": "sha256:07df4841390944b785592b2c323ece5aee7847b2ae646a7e8b087c00f7bcf07b",
  "generator": "article-pivot@0.1.0",
  "canonical_file": "./canonical.json",
  "content_file": "./how-to-explain-the-prediction-of-a-machine-learning-model.md",
  "source_file": "./how-to-explain-the-prediction-of-a-machine-learning-model-source.md",
  "bilingual_file": "./how-to-explain-the-prediction-of-a-machine-learning-model-bilingual.md",
  "translation_file": "./translations/zh-CN.json",
  "editorial_file": "./editorial/zh-CN.json",
  "publication_profile": "bilingual-zh-first.v1"
}
